MANIFEST.in
README
setup.py
django_videoembed.egg-info/PKG-INFO
django_videoembed.egg-info/SOURCES.txt
django_videoembed.egg-info/dependency_links.txt
django_videoembed.egg-info/not-zip-safe
django_videoembed.egg-info/top_level.txt
videoembed/__init__.py
videoembed/default_wrappers.py
videoembed/models.py
videoembed/registry.py
videoembed/templates/videoembed/embed_flowplayer.html
videoembed/templates/videoembed/embed_youtube.html
videoembed/templatetags/__init__.py
videoembed/templatetags/video.py