Metadata-Version: 1.1
Name: django-videoembed
Version: 0.3.1-1
Summary: Easy embedding videos with Django
Home-page: https://github.com/marcinn/django-videoembed
Author: Marcin Nowak
Author-email: marcin.j.nowak@gmail.com
License: UNKNOWN
Download-URL: https://github.com/marcinn/django-videoembed/archive/master.zip
Platform: UNKNOWN
Classifier: Development Status :: 3 - Alpha
Classifier: Environment :: Web Environment
Classifier: Intended Audience :: Developers
Classifier: License :: OSI Approved :: MIT License
Classifier: Operating System :: OS Independent
Classifier: Programming Language :: Python
Classifier: Framework :: Django
